keepitfresh.py
keepitfresh-1.0.2.dist-info/DESCRIPTION.rst
keepitfresh-1.0.2.dist-info/METADATA
keepitfresh-1.0.2.dist-info/RECORD
keepitfresh-1.0.2.dist-info/WHEEL
keepitfresh-1.0.2.dist-info/metadata.json
keepitfresh-1.0.2.dist-info/top_level.txt
