Metadata-Version: 2.0
Name: keepitfresh
Version: 1.0.2
Summary: A simpler way to freshen up your frozen applications.
Home-page: https://github.com/GandaG/keepitfresh
Author: Daniel Nunes
Author-email: daniel.henri.nunes@gmail.com
License: Apache 2.0
Keywords: installer,updater,frozen,application
Platform: UNKNOWN
Classifier: Development Status :: 3 - Alpha
Classifier: Intended Audience :: Developers
Classifier: Topic :: Software Development :: Build Tools
Classifier: License :: OSI Approved :: Apache Software License
Classifier: Operating System :: Microsoft :: Windows
Classifier: Operating System :: POSIX
Classifier: Operating System :: Unix
Classifier: Programming Language :: Python :: 3
Classifier: Programming Language :: Python :: 3 :: Only
Classifier: Programming Language :: Python :: 3.4
Classifier: Programming Language :: Python :: 3.5
Classifier: Programming Language :: Python :: 3.6
Classifier: Programming Language :: Python :: Implementation :: CPython
Classifier: Topic :: Software Development :: Libraries
Requires-Dist: packaging
Requires-Dist: patool
Provides-Extra: check
Requires-Dist: docutils; extra == 'check'
Requires-Dist: flake8; extra == 'check'
Requires-Dist: readme-renderer; extra == 'check'
Requires-Dist: collective.checkdocs; extra == 'check'
Requires-Dist: pygments; extra == 'check'
Requires-Dist: pylint; extra == 'check'
Requires-Dist: isort; extra == 'check'
Provides-Extra: docs
Requires-Dist: sphinx; extra == 'docs'
Requires-Dist: sphinx-rtd-theme; extra == 'docs'
Provides-Extra: test
Requires-Dist: pytest; extra == 'test'
Requires-Dist: pytest-cov; extra == 'test'
Requires-Dist: pytest-sugar; extra == 'test'
Requires-Dist: mock; extra == 'test'
